manen/__init__.py
manen/browser.py
manen/cli.py
manen/exceptions.py
manen/finder.py
manen/helpers.py
manen/page_object_model.py
manen/typing.py
manen/resource/__init__.py
manen/resource/brave.py
manen/resource/chrome.py
manen/resource/local.py
manen-0.2.0.dist-info/LICENSE
manen-0.2.0.dist-info/METADATA
manen-0.2.0.dist-info/WHEEL
manen-0.2.0.dist-info/entry_points.txt
manen-0.2.0.dist-info/top_level.txt
manen-0.2.0.dist-info/RECORD
