Metadata-Version: 2.1
Name: manen
Version: 0.2.0
Summary: A package around Selenium with an implementation of the page object model, an enhanced WebDriver and a CLI.
Home-page: https://github.com/kodaho/manen/
Author: kodaho
License: GPLv3
Project-URL: Issue Tracker, https://github.com/kodaho/manen/issues/
Project-URL: Changes, https://kodaho.github.io/manen/changelog.html
Project-URL: Documentation, https://kodaho.github.io/manen/
Project-URL: Source Code, https://github.com/kodaho/manen/
Keywords: automation,DOM,page object model,scraping,selenium,test
Platform: any
Classifier: Development Status :: 3 - Alpha
Classifier: Programming Language :: Python
Classifier: Programming Language :: Python :: 3
Requires-Python: >=3.6
Requires-Dist: dateparser (~=1.0.0)
Requires-Dist: polling2 (~=0.4.6)
Requires-Dist: pyyaml (~=5.4)
Requires-Dist: questionary (~=1.10.0)
Requires-Dist: requests (~=2.27.0)
Requires-Dist: selenium (>=3.141.0)
Provides-Extra: deploy
Requires-Dist: twine (~=3.7.1) ; extra == 'deploy'
Requires-Dist: wheel (~=0.37.1) ; extra == 'deploy'
Provides-Extra: doc
Requires-Dist: furo (>=2022.1.2) ; extra == 'doc'
Requires-Dist: sphinx-autobuild (>=2021.3.14) ; extra == 'doc'
Requires-Dist: sphinx-copybutton (~=0.5.0) ; extra == 'doc'
Requires-Dist: sphinx-inline-tabs (~=2022.1.2b11) ; extra == 'doc'
Requires-Dist: Sphinx (~=4.4.0) ; extra == 'doc'
Requires-Dist: nbsphinx (~=0.8.8) ; extra == 'doc'
Requires-Dist: ipython (~=8.0.1) ; extra == 'doc'
Provides-Extra: lint
Requires-Dist: black (~=21.12b0) ; extra == 'lint'
Requires-Dist: isort (~=5.10.1) ; extra == 'lint'
Requires-Dist: mypy (~=0.931) ; extra == 'lint'
Requires-Dist: pylint (~=2.12.2) ; extra == 'lint'
Requires-Dist: rstcheck (~=3.3.1) ; extra == 'lint'
Requires-Dist: types-dateparser (~=1.0.14) ; extra == 'lint'
Requires-Dist: types-PyYAML (~=6.0.4) ; extra == 'lint'
Provides-Extra: test
Requires-Dist: Jinja2 (~=3.0.3) ; extra == 'test'
Requires-Dist: pytest (~=6.2.5) ; extra == 'test'
